Workbook

Sheet Dashboard
A1: SkyConnect Airlines — Executive Dashboard
A2: Period: January 2026 | Currency: SAR
F4: Operational Inputs (editable)
F5: Flights Operated (month) | G5: 40
F6: Available Seat KM (ASK, million) | G6: 25
F7: Revenue Passenger KM (RPK, million) | G7: 18.5
A9: Total Revenue (SAR) | C9: Total OPEX (SAR) | E9: Net Profit (SAR)
A10: ='Profit and Loss'!C8 -> 1670000 | C10: ='Profit and Loss'!C20 -> 1088000 | E10: ='Profit and Loss'!C22 -> 582000
A12: Cash Position (SAR) | C12: Fuel Cost % of Revenue | E12: Net Profit Margin %
A13: ='Cash Flow'!C21 -> 12962000 | C13: ='Profit and Loss'!C11/'Profit and Loss'!C8 -> 0.20958084 | E13: ='Profit and Loss'!C22/'Profit and Loss'!C8 -> 0.34850299
A15: Load Factor % (RPK/ASK) | C15: Revenue per Flight (SAR) | E15: Cost per Flight (SAR)
A16: =G7/G6 -> 0.74 | C16: ='Profit and Loss'!C8/G5 -> 41750 | E16: ='Profit and Loss'!C20/G5 -> 27200
A21: Revenue Breakdown | D21: Expense Breakdown
A22: Account | B22: Amount | D22: Account | E22: Amount
A23: Passenger Revenue | B23: =SUMIF('Trial Balance'!$A$5:$A$30,4000,'Trial Balance'!$E$5:$E$30)-SUMIF('Trial Balance'!$A$5:$A$30,4000,'Trial Balance'!$D$5:$D$30) -> 1250000 | D23: Fuel Expense | E23: =SUMIF('Trial Balance'!$A$5:$A$30,5000,'Trial Balance'!$D$5:$D$30)-SUMIF('Trial Balance'!$A$5:$A$30,5000,'Trial Balance'!$E$5:$E$30) -> 350000
A24: Cargo Revenue | B24: =SUMIF('Trial Balance'!$A$5:$A$30,4010,'Trial Balance'!$E$5:$E$30)-SUMIF('Trial Balance'!$A$5:$A$30,4010,'Trial Balance'!$D$5:$D$30) -> 420000 | D24: Maintenance Expense | E24: =SUMIF('Trial Balance'!$A$5:$A$30,5100,'Trial Balance'!$D$5:$D$30)-SUMIF('Trial Balance'!$A$5:$A$30,5100,'Trial Balance'!$E$5:$E$30) -> 145000
A25: Charter Revenue | B25: =SUMIF('Trial Balance'!$A$5:$A$30,4020,'Trial Balance'!$E$5:$E$30)-SUMIF('Trial Balance'!$A$5:$A$30,4020,'Trial Balance'!$D$5:$D$30) -> 0 | D25: Salary Expense | E25: =SUMIF('Trial Balance'!$A$5:$A$30,5200,'Trial Balance'!$D$5:$D$30)-SUMIF('Trial Balance'!$A$5:$A$30,5200,'Trial Balance'!$E$5:$E$30) -> 280000
D26: Airport Charges | E26: =SUMIF('Trial Balance'!$A$5:$A$30,5300,'Trial Balance'!$D$5:$D$30)-SUMIF('Trial Balance'!$A$5:$A$30,5300,'Trial Balance'!$E$5:$E$30) -> 75000
D27: Marketing Expense | E27: =SUMIF('Trial Balance'!$A$5:$A$30,5400,'Trial Balance'!$D$5:$D$30)-SUMIF('Trial Balance'!$A$5:$A$30,5400,'Trial Balance'!$E$5:$E$30) -> 60000
D28: Insurance Expense | E28: =SUMIF('Trial Balance'!$A$5:$A$30,5500,'Trial Balance'!$D$5:$D$30)-SUMIF('Trial Balance'!$A$5:$A$30,5500,'Trial Balance'!$E$5:$E$30) -> 95000
D29: Office Rent | E29: =SUMIF('Trial Balance'!$A$5:$A$30,5600,'Trial Balance'!$D$5:$D$30)-SUMIF('Trial Balance'!$A$5:$A$30,5600,'Trial Balance'!$E$5:$E$30) -> 40000
D30: IT Expense | E30: =SUMIF('Trial Balance'!$A$5:$A$30,5700,'Trial Balance'!$D$5:$D$30)-SUMIF('Trial Balance'!$A$5:$A$30,5700,'Trial Balance'!$E$5:$E$30) -> 25000
D31: Utilities Expense | E31: =SUMIF('Trial Balance'!$A$5:$A$30,5800,'Trial Balance'!$D$5:$D$30)-SUMIF('Trial Balance'!$A$5:$A$30,5800,'Trial Balance'!$E$5:$E$30) -> 18000

Sheet Chart of Accounts
A1: SkyConnect Airlines — Chart of Accounts
A2: Base Currency: SAR | Financial Year: Jan-Dec
A4: Account Code | B4: Account Name | C4: Type | D4: Statement Section
A5: 1010 | B5: Cash | C5: Asset | D5: Current Asset
A6: 1020 | B6: Bank | C6: Asset | D6: Current Asset
A7: 1100 | B7: Accounts Receivable | C7: Asset | D7: Current Asset
A8: 1200 | B8: Inventory | C8: Asset | D8: Current Asset
A9: 1500 | B9: Prepaid Expenses | C9: Asset | D9: Current Asset
A10: 1550 | B10: Lease Deposit | C10: Asset | D10: Non-Current Asset
A11: 1600 | B11: Aircraft | C11: Asset | D11: Non-Current Asset
A12: 1700 | B12: Ground Equipment | C12: Asset | D12: Non-Current Asset
A13: 1750 | B13: Office Equipment | C13: Asset | D13: Non-Current Asset
A14: 2000 | B14: Accounts Payable | C14: Liability | D14: Current Liability
A15: 2100 | B15: Accrued Expenses | C15: Liability | D15: Current Liability
A16: 2200 | B16: Lease Liability | C16: Liability | D16: Non-Current Liability
... A30: 5800 | B30: Utilities Expense | C30: Expense | D30: Operating Expense

Sheet Transactions
A1: SkyConnect Airlines — Transaction Log (Dynamic Input Table)
A2: Add new rows to the table below — Trial Balance, P&L, Balance Sheet and Dashboard update automatically.
A4: Date | B4: Description | C4: Debit Account Code | D4: Debit Account Name | E4: Credit Account Code | F4: Credit Account Name | G4: Amount (SAR)
A5: 2026-01-01 | B5: Owner invested capital | C5: 1020 | D5: =IFERROR(VLOOKUP(C5,COA,2,FALSE()),"") -> Bank | E5: 3000 | F5: =IFERROR(VLOOKUP(E5,COA,2,FALSE()),"") -> Share Capital | G5: 15000000
A6: 2026-01-02 | B6: Purchased office furniture | C6: 1750 | D6: =IFERROR(VLOOKUP(C6,COA,2,FALSE()),"") -> Office Equipment | E6: 1020 | F6: =IFERROR(VLOOKUP(E6,COA,2,FALSE()),"") -> Bank | G6: 120000
A7: 2026-01-03 | B7: Aircraft lease deposit | C7: 1550 | D7: =IFERROR(VLOOKUP(C7,COA,2,FALSE()),"") -> Lease Deposit | E7: 1020 | F7: =IFERROR(VLOOKUP(E7,COA,2,FALSE()),"") -> Bank | G7: 2500000
A8: 2026-01-04 | B8: Fuel purchased | C8: 5000 | D8: =IFERROR(VLOOKUP(C8,COA,2,FALSE()),"") -> Fuel Expense | E8: 1020 | F8: =IFERROR(VLOOKUP(E8,COA,2,FALSE()),"") -> Bank | G8: 350000
A9: 2026-01-05 | B9: Passenger ticket sales | C9: 1020 | D9: =IFERROR(VLOOKUP(C9,COA,2,FALSE()),"") -> Bank | E9: 4000 | F9: =IFERROR(VLOOKUP(E9,COA,2,FALSE()),"") -> Passenger Revenue | G9: 1250000
A10: 2026-01-06 | B10: Cargo revenue | C10: 1020 | D10: =IFERROR(VLOOKUP(C10,COA,2,FALSE()),"") -> Bank | E10: 4010 | F10: =IFERROR(VLOOKUP(E10,COA,2,FALSE()),"") -> Cargo Revenue | G10: 420000
A11: 2026-01-07 | B11: Airport landing fees | C11: 5300 | D11: =IFERROR(VLOOKUP(C11,COA,2,FALSE()),"") -> Airport Charges | E11: 1020 | F11: =IFERROR(VLOOKUP(E11,COA,2,FALSE()),"") -> Bank | G11: 75000
A12: 2026-01-08 | B12: Crew salaries | C12: 5200 | D12: =IFERROR(VLOOKUP(C12,COA,2,FALSE()),"") -> Salary Expense | E12: 1020 | F12: =IFERROR(VLOOKUP(E12,COA,2,FALSE()),"") -> Bank | G12: 280000
A13: 2026-01-09 | B13: Aircraft maintenance | C13: 5100 | D13: =IFERROR(VLOOKUP(C13,COA,2,FALSE()),"") -> Maintenance Expense | E13: 1020 | F13: =IFERROR(VLOOKUP(E13,COA,2,FALSE()),"") -> Bank | G13: 145000
A14: 2026-01-10 | B14: Insurance premium | C14: 5500 | D14: =IFERROR(VLOOKUP(C14,COA,2,FALSE()),"") -> Insurance Expense | E14: 1020 | F14: =IFERROR(VLOOKUP(E14,COA,2,FALSE()),"") -> Bank | G14: 95000
A15: 2026-01-11 | B15: Marketing campaign | C15: 5400 | D15: =IFERROR(VLOOKUP(C15,COA,2,FALSE()),"") -> Marketing Expense | E15: 1020 | F15: =IFERROR(VLOOKUP(E15,COA,2,FALSE()),"") -> Bank | G15: 60000
A16: 2026-01-12 | B16: Office rent | C16: 5600 | D16: =IFERROR(VLOOKUP(C16,COA,2,FALSE()),"") -> Office Rent | E16: 1020 | F16: =IFERROR(VLOOKUP(E16,COA,2,FALSE()),"") -> Bank | G16: 40000
... A18: 2026-01-14 | B18: IT software subscription | C18: 5700 | D18: =IFERROR(VLOOKUP(C18,COA,2,FALSE()),"") -> IT Expense | E18: 1020 | F18: =IFERROR(VLOOKUP(E18,COA,2,FALSE()),"") -> Bank | G18: 25000

Sheet Trial Balance
A1: SkyConnect Airlines — Trial Balance
A2: Auto-calculated from Transactions using SUMIF
A4: Account Code | B4: Account Name | C4: Type | D4: Debit (SAR) | E4: Credit (SAR)
A5: 1010 | B5: =VLOOKUP(A5,COA,2,FALSE()) -> Cash | C5: =VLOOKUP(A5,COA,3,FALSE()) -> Asset | D5: =SUMIF(Transactions[Debit Account Code],A5,Transactions[Amount (SAR)]) -> 0 | E5: =SUMIF(Transactions[Credit Account Code],A5,Transactions[Amount (SAR)]) -> 0
A6: 1020 | B6: =VLOOKUP(A6,COA,2,FALSE()) -> Bank | C6: =VLOOKUP(A6,COA,3,FALSE()) -> Asset | D6: =SUMIF(Transactions[Debit Account Code],A6,Transactions[Amount (SAR)]) -> 16670000 | E6: =SUMIF(Transactions[Credit Account Code],A6,Transactions[Amount (SAR)]) -> 3708000
A7: 1100 | B7: =VLOOKUP(A7,COA,2,FALSE()) -> Accounts Receivable | C7: =VLOOKUP(A7,COA,3,FALSE()) -> Asset | D7: =SUMIF(Transactions[Debit Account Code],A7,Transactions[Amount (SAR)]) -> 0 | E7: =SUMIF(Transactions[Credit Account Code],A7,Transactions[Amount (SAR)]) -> 0
A8: 1200 | B8: =VLOOKUP(A8,COA,2,FALSE()) -> Inventory | C8: =VLOOKUP(A8,COA,3,FALSE()) -> Asset | D8: =SUMIF(Transactions[Debit Account Code],A8,Transactions[Amount (SAR)]) -> 0 | E8: =SUMIF(Transactions[Credit Account Code],A8,Transactions[Amount (SAR)]) -> 0
A9: 1500 | B9: =VLOOKUP(A9,COA,2,FALSE()) -> Prepaid Expenses | C9: =VLOOKUP(A9,COA,3,FALSE()) -> Asset | D9: =SUMIF(Transactions[Debit Account Code],A9,Transactions[Amount (SAR)]) -> 0 | E9: =SUMIF(Transactions[Credit Account Code],A9,Transactions[Amount (SAR)]) -> 0
A10: 1550 | B10: =VLOOKUP(A10,COA,2,FALSE()) -> Lease Deposit | C10: =VLOOKUP(A10,COA,3,FALSE()) -> Asset | D10: =SUMIF(Transactions[Debit Account Code],A10,Transactions[Amount (SAR)]) -> 2500000 | E10: =SUMIF(Transactions[Credit Account Code],A10,Transactions[Amount (SAR)]) -> 0
A11: 1600 | B11: =VLOOKUP(A11,COA,2,FALSE()) -> Aircraft | C11: =VLOOKUP(A11,COA,3,FALSE()) -> Asset | D11: =SUMIF(Transactions[Debit Account Code],A11,Transactions[Amount (SAR)]) -> 0 | E11: =SUMIF(Transactions[Credit Account Code],A11,Transactions[Amount (SAR)]) -> 0
A12: 1700 | B12: =VLOOKUP(A12,COA,2,FALSE()) -> Ground Equipment | C12: =VLOOKUP(A12,COA,3,FALSE()) -> Asset | D12: =SUMIF(Transactions[Debit Account Code],A12,Transactions[Amount (SAR)]) -> 0 | E12: =SUMIF(Transactions[Credit Account Code],A12,Transactions[Amount (SAR)]) -> 0
A13: 1750 | B13: =VLOOKUP(A13,COA,2,FALSE()) -> Office Equipment | C13: =VLOOKUP(A13,COA,3,FALSE()) -> Asset | D13: =SUMIF(Transactions[Debit Account Code],A13,Transactions[Amount (SAR)]) -> 120000 | E13: =SUMIF(Transactions[Credit Account Code],A13,Transactions[Amount (SAR)]) -> 0
A14: 2000 | B14: =VLOOKUP(A14,COA,2,FALSE()) -> Accounts Payable | C14: =VLOOKUP(A14,COA,3,FALSE()) -> Liability | D14: =SUMIF(Transactions[Debit Account Code],A14,Transactions[Amount (SAR)]) -> 0 | E14: =SUMIF(Transactions[Credit Account Code],A14,Transactions[Amount (SAR)]) -> 0
A15: 2100 | B15: =VLOOKUP(A15,COA,2,FALSE()) -> Accrued Expenses | C15: =VLOOKUP(A15,COA,3,FALSE()) -> Liability | D15: =SUMIF(Transactions[Debit Account Code],A15,Transactions[Amount (SAR)]) -> 0 | E15: =SUMIF(Transactions[Credit Account Code],A15,Transactions[Amount (SAR)]) -> 0
A16: 2200 | B16: =VLOOKUP(A16,COA,2,FALSE()) -> Lease Liability | C16: =VLOOKUP(A16,COA,3,FALSE()) -> Liability | D16: =SUMIF(Transactions[Debit Account Code],A16,Transactions[Amount (SAR)]) -> 0 | E16: =SUMIF(Transactions[Credit Account Code],A16,Transactions[Amount (SAR)]) -> 0
... A30: 5800 | B30: =VLOOKUP(A30,COA,2,FALSE()) -> Utilities Expense | C30: =VLOOKUP(A30,COA,3,FALSE()) -> Expense | D30: =SUMIF(Transactions[Debit Account Code],A30,Transactions[Amount (SAR)]) -> 18000 | E30: =SUMIF(Transactions[Credit Account Code],A30,Transactions[Amount (SAR)]) -> 0
B31: TOTAL | D31: =SUM(D5:D30) -> 20378000 | E31: =SUM(E5:E30) -> 20378000
B33: Check (Debit = Credit): | D33: =IF(D31=E31,"Balanced ✓","OUT OF BALANCE") -> Balanced ✓

Sheet Profit and Loss
A1: SkyConnect Airlines — Profit & Loss Statement
A2: For the period ended 31-Jan-2026 (SAR)
A4: REVENUE
A5: Passenger Revenue | C5: =SUMIF('Trial Balance'!$A$5:$A$30,4000,'Trial Balance'!$E$5:$E$30)-SUMIF('Trial Balance'!$A$5:$A$30,4000,'Trial Balance'!$D$5:$D$30) -> 1250000
A6: Cargo Revenue | C6: =SUMIF('Trial Balance'!$A$5:$A$30,4010,'Trial Balance'!$E$5:$E$30)-SUMIF('Trial Balance'!$A$5:$A$30,4010,'Trial Balance'!$D$5:$D$30) -> 420000
A7: Charter Revenue | C7: =SUMIF('Trial Balance'!$A$5:$A$30,4020,'Trial Balance'!$E$5:$E$30)-SUMIF('Trial Balance'!$A$5:$A$30,4020,'Trial Balance'!$D$5:$D$30) -> 0
A8: Total Revenue | C8: =SUM(C5:C7) -> 1670000
A10: OPERATING EXPENSES
A11: Fuel Expense | C11: =SUMIF('Trial Balance'!$A$5:$A$30,5000,'Trial Balance'!$D$5:$D$30)-SUMIF('Trial Balance'!$A$5:$A$30,5000,'Trial Balance'!$E$5:$E$30) -> 350000
A12: Maintenance Expense | C12: =SUMIF('Trial Balance'!$A$5:$A$30,5100,'Trial Balance'!$D$5:$D$30)-SUMIF('Trial Balance'!$A$5:$A$30,5100,'Trial Balance'!$E$5:$E$30) -> 145000
A13: Salary Expense | C13: =SUMIF('Trial Balance'!$A$5:$A$30,5200,'Trial Balance'!$D$5:$D$30)-SUMIF('Trial Balance'!$A$5:$A$30,5200,'Trial Balance'!$E$5:$E$30) -> 280000
A14: Airport Charges | C14: =SUMIF('Trial Balance'!$A$5:$A$30,5300,'Trial Balance'!$D$5:$D$30)-SUMIF('Trial Balance'!$A$5:$A$30,5300,'Trial Balance'!$E$5:$E$30) -> 75000
A15: Marketing Expense | C15: =SUMIF('Trial Balance'!$A$5:$A$30,5400,'Trial Balance'!$D$5:$D$30)-SUMIF('Trial Balance'!$A$5:$A$30,5400,'Trial Balance'!$E$5:$E$30) -> 60000
A16: Insurance Expense | C16: =SUMIF('Trial Balance'!$A$5:$A$30,5500,'Trial Balance'!$D$5:$D$30)-SUMIF('Trial Balance'!$A$5:$A$30,5500,'Trial Balance'!$E$5:$E$30) -> 95000
A17: Office Rent | C17: =SUMIF('Trial Balance'!$A$5:$A$30,5600,'Trial Balance'!$D$5:$D$30)-SUMIF('Trial Balance'!$A$5:$A$30,5600,'Trial Balance'!$E$5:$E$30) -> 40000
A18: IT Expense | C18: =SUMIF('Trial Balance'!$A$5:$A$30,5700,'Trial Balance'!$D$5:$D$30)-SUMIF('Trial Balance'!$A$5:$A$30,5700,'Trial Balance'!$E$5:$E$30) -> 25000
A19: Utilities Expense | C19: =SUMIF('Trial Balance'!$A$5:$A$30,5800,'Trial Balance'!$D$5:$D$30)-SUMIF('Trial Balance'!$A$5:$A$30,5800,'Trial Balance'!$E$5:$E$30) -> 18000
A20: Total Operating Expenses | C20: =SUM(C11:C19) -> 1088000
A22: NET PROFIT / (LOSS) | C22: =C8-C20 -> 582000

Sheet Balance Sheet
A1: SkyConnect Airlines — Balance Sheet
A2: As at 31-Jan-2026 (SAR)
A4: ASSETS
A5: Cash | C5: =SUMIF('Trial Balance'!$A$5:$A$30,1010,'Trial Balance'!$D$5:$D$30)-SUMIF('Trial Balance'!$A$5:$A$30,1010,'Trial Balance'!$E$5:$E$30) -> 0
A6: Bank | C6: =SUMIF('Trial Balance'!$A$5:$A$30,1020,'Trial Balance'!$D$5:$D$30)-SUMIF('Trial Balance'!$A$5:$A$30,1020,'Trial Balance'!$E$5:$E$30) -> 12962000
A7: Accounts Receivable | C7: =SUMIF('Trial Balance'!$A$5:$A$30,1100,'Trial Balance'!$D$5:$D$30)-SUMIF('Trial Balance'!$A$5:$A$30,1100,'Trial Balance'!$E$5:$E$30) -> 0
A8: Inventory | C8: =SUMIF('Trial Balance'!$A$5:$A$30,1200,'Trial Balance'!$D$5:$D$30)-SUMIF('Trial Balance'!$A$5:$A$30,1200,'Trial Balance'!$E$5:$E$30) -> 0
A9: Prepaid Expenses | C9: =SUMIF('Trial Balance'!$A$5:$A$30,1500,'Trial Balance'!$D$5:$D$30)-SUMIF('Trial Balance'!$A$5:$A$30,1500,'Trial Balance'!$E$5:$E$30) -> 0
A10: Lease Deposit | C10: =SUMIF('Trial Balance'!$A$5:$A$30,1550,'Trial Balance'!$D$5:$D$30)-SUMIF('Trial Balance'!$A$5:$A$30,1550,'Trial Balance'!$E$5:$E$30) -> 2500000
A11: Aircraft | C11: =SUMIF('Trial Balance'!$A$5:$A$30,1600,'Trial Balance'!$D$5:$D$30)-SUMIF('Trial Balance'!$A$5:$A$30,1600,'Trial Balance'!$E$5:$E$30) -> 0
A12: Ground Equipment | C12: =SUMIF('Trial Balance'!$A$5:$A$30,1700,'Trial Balance'!$D$5:$D$30)-SUMIF('Trial Balance'!$A$5:$A$30,1700,'Trial Balance'!$E$5:$E$30) -> 0
A13: Office Equipment | C13: =SUMIF('Trial Balance'!$A$5:$A$30,1750,'Trial Balance'!$D$5:$D$30)-SUMIF('Trial Balance'!$A$5:$A$30,1750,'Trial Balance'!$E$5:$E$30) -> 120000
A14: Total Assets | C14: =SUM(C5:C13) -> 15582000
A16: LIABILITIES
A17: Accounts Payable | C17: =SUMIF('Trial Balance'!$A$5:$A$30,2000,'Trial Balance'!$E$5:$E$30)-SUMIF('Trial Balance'!$A$5:$A$30,2000,'Trial Balance'!$D$5:$D$30) -> 0
A18: Accrued Expenses | C18: =SUMIF('Trial Balance'!$A$5:$A$30,2100,'Trial Balance'!$E$5:$E$30)-SUMIF('Trial Balance'!$A$5:$A$30,2100,'Trial Balance'!$D$5:$D$30) -> 0
A19: Lease Liability | C19: =SUMIF('Trial Balance'!$A$5:$A$30,2200,'Trial Balance'!$E$5:$E$30)-SUMIF('Trial Balance'!$A$5:$A$30,2200,'Trial Balance'!$D$5:$D$30) -> 0
A20: Total Liabilities | C20: =SUM(C17:C19) -> 0
A22: EQUITY
A23: Share Capital | C23: =SUMIF('Trial Balance'!$A$5:$A$30,3000,'Trial Balance'!$E$5:$E$30)-SUMIF('Trial Balance'!$A$5:$A$30,3000,'Trial Balance'!$D$5:$D$30) -> 15000000
A24: Retained Earnings (current period profit) | C24: ='Profit and Loss'!C22 -> 582000
A25: Total Equity | C25: =SUM(C23:C24) -> 15582000
A27: Total Liabilities + Equity | C27: =C20+C25 -> 15582000
A29: Check (Assets = Liabilities + Equity): | C29: =IF(ROUND(C14-C27,2)=0,"Balanced ✓","OUT OF BALANCE") -> Balanced ✓

Sheet Cash Flow
A1: SkyConnect Airlines — Cash Flow Statement
A2: For the period ended 31-Jan-2026 (SAR) — Direct Method
A4: CASH FLOW FROM OPERATING ACTIVITIES
A5: Cash received from customers (Passenger, Cargo, Charter revenue) | C5: ='Profit and Loss'!C8 -> 1670000
A6: Cash paid for operating expenses | C6: =-'Profit and Loss'!C20 -> -1088000
A7: Net Cash from Operating Activities | C7: =SUM(C5:C6) -> 582000
A9: CASH FLOW FROM INVESTING ACTIVITIES
A10: Purchase of Office Equipment | C10: =-(SUMIF('Trial Balance'!$A$5:$A$30,1750,'Trial Balance'!$D$5:$D$30)-SUMIF('Trial Balance'!$A$5:$A$30,1750,'Trial Balance'!$E$5:$E$30)) -> -120000
A11: Aircraft lease deposit paid | C11: =-(SUMIF('Trial Balance'!$A$5:$A$30,1550,'Trial Balance'!$D$5:$D$30)-SUMIF('Trial Balance'!$A$5:$A$30,1550,'Trial Balance'!$E$5:$E$30)) -> -2500000
A12: Purchase of Aircraft | C12: =-(SUMIF('Trial Balance'!$A$5:$A$30,1600,'Trial Balance'!$D$5:$D$30)-SUMIF('Trial Balance'!$A$5:$A$30,1600,'Trial Balance'!$E$5:$E$30)) -> 0
A13: Purchase of Ground Equipment | C13: =-(SUMIF('Trial Balance'!$A$5:$A$30,1700,'Trial Balance'!$D$5:$D$30)-SUMIF('Trial Balance'!$A$5:$A$30,1700,'Trial Balance'!$E$5:$E$30)) -> 0
A14: Net Cash used in Investing Activities | C14: =SUM(C10:C13) -> -2620000
A16: CASH FLOW FROM FINANCING ACTIVITIES
A17: Owner capital invested | C17: =SUMIF('Trial Balance'!$A$5:$A$30,3000,'Trial Balance'!$E$5:$E$30)-SUMIF('Trial Balance'!$A$5:$A$30,3000,'Trial Balance'!$D$5:$D$30) -> 15000000
A18: Net Cash from Financing Activities | C18: =SUM(C17:C17) -> 15000000
A20: NET INCREASE IN CASH | C20: =C7+C14+C18 -> 12962000
A21: Closing Cash & Bank Balance | C21: ='Balance Sheet'!C5+'Balance Sheet'!C6 -> 12962000
